fritzbox_api/__init__.py
fritzbox_api/devices.py
fritzbox_api/fritzbox.py
fritzbox_api/streaming_rate.py
fritzbox_api/utils.py
fritzbox_api-0.1.0.dist-info/WHEEL
fritzbox_api-0.1.0.dist-info/METADATA
fritzbox_api-0.1.0.dist-info/RECORD
