Metadata-Version: 2.1
Name: fritzbox-api
Version: 0.1.0
Summary: REST API implementation for the Fritzbox router
Author: Oskar Herz
Author-email: herz@gmail.de
Requires-Python: >=3.7,<4.0
Classifier: Programming Language :: Python :: 3
Classifier: Programming Language :: Python :: 3.7
Classifier: Programming Language :: Python :: 3.8
Classifier: Programming Language :: Python :: 3.9
Requires-Dist: requests (>=2.25.0,<3.0.0)
